{"textures":{"0":"modelengine:entity/tengu"},"elements":[{"from":[9.238095,2.7619042,6.714286],"to":[10.952381,4.4761906,9.0],"rotation":{"angle":0.0,"axis":"y","origin":[14.666667,1.333333,7.285714]},"faces":{"east":{"uv":[9.75,4.75,9.25,5.125],"rotation":0,"texture":"#0","tintindex":0},"south":{"uv":[9.75,3.0,9.375,3.375],"rotation":0,"texture":"#0","tintindex":0},"north":{"uv":[9.75,2.125,9.375,2.5],"rotation":0,"texture":"#0","tintindex":0},"west":{"uv":[1.0,7.5,0.5,7.875],"rotation":0,"texture":"#0","tintindex":0},"up":{"uv":[2.5,9.75,2.875,9.25],"rotation":0,"texture":"#0","tintindex":0},"down":{"uv":[9.25,5.125,9.625,5.625],"rotation":0,"texture":"#0","tintindex":0}}},{"from":[8.095238,4.4761906,6.142857],"to":[11.523809,10.190476,9.571428],"rotation":{"angle":0.0,"axis":"y","origin":[14.666667,7.047619,7.285714]},"faces":{"east":{"uv":[6.5,6.0,5.75,7.25],"rotation":0,"texture":"#0","tintindex":0},"south":{"uv":[3.5,6.0,2.75,7.25],"rotation":0,"texture":"#0","tintindex":0},"north":{"uv":[2.0,6.0,1.25,7.25],"rotation":0,"texture":"#0","tintindex":0},"west":{"uv":[2.75,6.0,2.0,7.25],"rotation":0,"texture":"#0","tintindex":0},"up":{"uv":[8.0,7.875,8.75,7.125],"rotation":0,"texture":"#0","tintindex":0},"down":{"uv":[8.125,2.25,8.875,3.0],"rotation":0,"texture":"#0","tintindex":0}}}],"display":{"head":{"translation":[0.0,-6.4,0.0],"scale":[4.0,4.0,4.0]}}}